django_earthdistance/__init__.py
django_earthdistance/models.py
tests/__init__.py
tests/models.py
tests/tests.py
django_earthdistance-1.1.3.dist-info/AUTHORS.rst
django_earthdistance-1.1.3.dist-info/LICENSE
django_earthdistance-1.1.3.dist-info/METADATA
django_earthdistance-1.1.3.dist-info/WHEEL
django_earthdistance-1.1.3.dist-info/top_level.txt
django_earthdistance-1.1.3.dist-info/RECORD
