Metadata-Version: 2.1
Name: django-earthdistance
Version: 1.1.3
Summary: Add support for PostgreSQL earthdistance extension to Django
Home-page: https://github.com/jneight/django-earthdistance
Author: Javier Cordero Martinez
Author-email: github@j2i.me
License: Apache 2.0
Classifier: Environment :: Web Environment
Classifier: Framework :: Django
Classifier: Intended Audience :: Developers
Classifier: License :: OSI Approved :: Apache Software License
Classifier: Operating System :: OS Independent
Classifier: Programming Language :: Python
Classifier: Topic :: Software Development :: Libraries :: Application Frameworks
License-File: LICENSE
License-File: AUTHORS.rst
Requires-Dist: django (>=1.8)
